vessel_express/__init__.py
vessel_express/_dock_widget.py
vessel_express/_reader.py
vessel_express/utils.py
vessel_express/_tests/__init__.py
vessel_express/_tests/test_reader.py
vessel_express/_tests/test_vessel_express.py
vessel_express_napari-0.0.9.dist-info/LICENSE
vessel_express_napari-0.0.9.dist-info/METADATA
vessel_express_napari-0.0.9.dist-info/WHEEL
vessel_express_napari-0.0.9.dist-info/entry_points.txt
vessel_express_napari-0.0.9.dist-info/top_level.txt
vessel_express_napari-0.0.9.dist-info/RECORD
