Metadata-Version: 2.1
Name: vessel-express-napari
Version: 0.0.9
Summary: A simple plugin for 3D vessel segmentation
Home-page: https://github.com/MMV-Lab/vessel-express-napari
Author: Lennart Kowitz
Author-email: lennart.kowitz@isas.de
License: BSD-3-Clause
Project-URL: Bug Tracker, https://github.com/MMV-Lab/vessel-express-napari/issues
Project-URL: Documentation, https://github.com/MMV-Lab/vessel-express-napari#README.md
Project-URL: Source Code, https://github.com/MMV-Lab/vessel-express-napari
Project-URL: User Support, https://github.com/MMV-Lab/vessel-express-napari/issues
Classifier: Development Status :: 2 - Pre-Alpha
Classifier: Intended Audience :: Developers
Classifier: Framework :: napari
Classifier: Topic :: Software Development :: Testing
Classifier: Programming Language :: Python
Classifier: Programming Language :: Python :: 3
Classifier: Programming Language :: Python :: 3.7
Classifier: Programming Language :: Python :: 3.8
Classifier: Programming Language :: Python :: 3.9
Classifier: Operating System :: OS Independent
Classifier: License :: OSI Approved :: BSD License
Requires-Python: >=3.7
License-File: LICENSE
Requires-Dist: napari-plugin-engine (>=0.1.4)
Requires-Dist: numpy
Requires-Dist: itk
Requires-Dist: scikit-image
Requires-Dist: aicssegmentation
